ani_cli/__init__.py
ani_cli/__main__.py
ani_cli-0.3.3.dist-info/entry_points.txt
ani_cli-0.3.3.dist-info/LICENSE
ani_cli-0.3.3.dist-info/WHEEL
ani_cli-0.3.3.dist-info/METADATA
ani_cli-0.3.3.dist-info/RECORD
