Metadata-Version: 2.1
Name: ani-cli
Version: 0.3.3
Summary: 
Author: sleepntsheep
Author-email: sheep@papangkorn.com
Requires-Python: >=3.7,<4.0
Classifier: Programming Language :: Python :: 3
Classifier: Programming Language :: Python :: 3.10
Classifier: Programming Language :: Python :: 3.7
Classifier: Programming Language :: Python :: 3.8
Classifier: Programming Language :: Python :: 3.9
Requires-Dist: InquirerPy (>=0.3.0,<0.4.0)
Requires-Dist: requests (>=2.26.0,<3.0.0)
